mojo/collections/__init__.py
mojo/collections/caseinsensitivebytesdict.py
mojo/collections/caseinsensitivestringdict.py
mojo/collections/context.py
mojo/collections/contextpaths.py
mojo/collections/contextuser.py
mojo/collections/dictmap.py
mojo/collections/helpers.py
mojo/collections/mergemap.py
mojo/collections/singletons.py
mojo/collections/wellknown.py
mojo_collections-2.0.24.dist-info/LICENSE.txt
mojo_collections-2.0.24.dist-info/METADATA
mojo_collections-2.0.24.dist-info/WHEEL
mojo_collections-2.0.24.dist-info/RECORD
